kanuni_layer_sdk/__init__.py
kanuni_layer_sdk/main.py
kanuni_layer_sdk/assets/disabilities.json
kanuni_layer_sdk/modules/__init__.py
kanuni_layer_sdk/modules/redactor.py
kanuni_layer_sdk/modules/validator.py
kanuni_layer_sdk-0.2.0.dist-info/METADATA
kanuni_layer_sdk-0.2.0.dist-info/WHEEL
kanuni_layer_sdk-0.2.0.dist-info/top_level.txt
kanuni_layer_sdk-0.2.0.dist-info/RECORD
