Metadata-Version: 2.4
Name: kanuni-layer-sdk
Version: 0.2.0
Summary: A SDK for Kanuni
Author-email: Kanuni Team <team@kanuni.com>
License-Expression: MIT
Keywords: kanuni,sdk,pwd,disability
Requires-Python: >=3.12
Requires-Dist: privacy-prompt-library>=1.2.0
Provides-Extra: dev
Requires-Dist: ruff<1.0,>=0.12; extra == "dev"
